samtesred_skorozvon/__init__.py
samtesred_skorozvon/main.py
samtesred_skorozvon-1.0.0.dist-info/METADATA
samtesred_skorozvon-1.0.0.dist-info/WHEEL
samtesred_skorozvon-1.0.0.dist-info/top_level.txt
samtesred_skorozvon-1.0.0.dist-info/RECORD
