Metadata-Version: 2.1
Name: samtesred_skorozvon
Version: 1.0.0
Summary: This is my first module
Home-page: https://github.com/CREATINAAA/my_lib/blob/main/my_lib.tar.xz
Author: samtesred
Author-email: samtesred@gmail.com
Keywords: example python
Classifier: Programming Language :: Python :: 3.11
Classifier: License :: OSI Approved :: MIT License
Classifier: Operating System :: OS Independent
Requires-Python: >=3.7
Requires-Dist: requests >=2.25.1
